<?xml version="1.0" encoding="ISO-8859-1" ?> 
<TheBrainSimpleXML>
  <Tht id="22" name="Steering" icon="" color="" hint="" pbv="9322438376219"
    modificationDate="4-Apr-2014 4:31 PM"
    authorName="Razie"
    authorEmail="razie@razie.com" />
  <Tht id="21" name="Brake steering" icon="" color="" hint="Post" /> 
  <Tht id="20" name="Steering a dirt bike" icon="" color="" hint="Post" /> 

  <Tht id="13" name="Basic off-road skills" icon="" color="" hint="Post" /> 

  <Tht id="27" name="Dirt bike Cornering" icon="" color="" hint="" /> 

  <Tht id="18" name="Accelerating" icon="" color="" hint="Post" /> 
  <Tht id="17" name="Braking" icon="" color="" hint="Post" /> 
  <Tht id="23" name="Crossing small logs and obstacles" icon="" color="" hint="Post" /> 
  <Tht id="14" name="Standing position" icon="" color="" hint="Post" /> 
  <Tht id="19" name="Throttle clutch control" icon="" color="" hint="Post" /> 
  <Tht id="16" name="Traction" icon="" color="" hint="Post" /> 
  <Tht id="15" name="Weight Transfer" icon="" color="" hint="Post" /> 

  <Link idA="22" idB="21" type="CHILD" /> 
  <Link idA="22" idB="20" type="CHILD" /> 
  <Link idA="13" idB="14" type="CHILD" /> 
  <Link idA="13" idB="15" type="CHILD" /> 
  <Link idA="13" idB="16" type="CHILD" /> 
  <Link idA="13" idB="17" type="CHILD" /> 
  <Link idA="13" idB="18" type="CHILD" /> 
  <Link idA="13" idB="19" type="CHILD" /> 
  <Link idA="13" idB="23" type="CHILD" /> 
  <Link idA="13" idB="22" type="PARENT" /> 
  <Link idA="22" idB="27" type="JUMP" /> 

  <Content href="thoughtData/22.html" />
</TheBrainSimpleXML>
